huggingface_zeusdb/__init__.py
huggingface_zeusdb-0.0.0.dist-info/METADATA
huggingface_zeusdb-0.0.0.dist-info/WHEEL
huggingface_zeusdb-0.0.0.dist-info/top_level.txt
huggingface_zeusdb-0.0.0.dist-info/RECORD
